PyValuation/__init__.py
PyValuation/dcf.py
PyValuation/financialdata.py
PyValuation/portfoliovaluation.py
PyValuation/relativevaluation.py
PyValuation/valuation.py
PyValuation/valuationcharts.py
PyValuation/.ipynb_checkpoints/dcf-checkpoint.py
PyValuation/.ipynb_checkpoints/financialdata-checkpoint.py
PyValuation/.ipynb_checkpoints/portfoliovaluation-checkpoint.py
PyValuation/.ipynb_checkpoints/relativevaluation-checkpoint.py
PyValuation/.ipynb_checkpoints/valuation-checkpoint.py
PyValuation/.ipynb_checkpoints/valuationcharts-checkpoint.py
PyValuation/__pycache__/__init__.cpython-38.pyc
PyValuation/__pycache__/__init__.cpython-39.pyc
PyValuation/__pycache__/dcf.cpython-38.pyc
PyValuation/__pycache__/financialdata.cpython-38.pyc
PyValuation/__pycache__/financialdata.cpython-39.pyc
PyValuation/__pycache__/portfoliovaluation.cpython-38.pyc
PyValuation/__pycache__/relativevaluation.cpython-38.pyc
PyValuation/__pycache__/valuation.cpython-38.pyc
PyValuation/__pycache__/valuationcharts.cpython-38.pyc
PyValuation-0.1.2.dist-info/METADATA
PyValuation-0.1.2.dist-info/WHEEL
PyValuation-0.1.2.dist-info/top_level.txt
PyValuation-0.1.2.dist-info/RECORD
