Metadata-Version: 2.1
Name: PyValuation
Version: 0.1.2
Summary: Demo library
Home-page: https://PyValuation.readthedocs.io/
Author: Jason DiBiase
Author-email: dibiasej3@gmail.com
License: MIT
Classifier: Intended Audience :: Developers
Classifier: License :: OSI Approved :: MIT License
Classifier: Programming Language :: Python
Classifier: Programming Language :: Python :: 3
Classifier: Programming Language :: Python :: 3.6
Classifier: Programming Language :: Python :: 3.7
Classifier: Programming Language :: Python :: 3.8
Classifier: Programming Language :: Python :: 3.9
Classifier: Operating System :: OS Independent
Requires-Dist: numpy
Requires-Dist: yfinance
Requires-Dist: pandas
Requires-Dist: bs4
Requires-Dist: requests
Requires-Dist: numpy-financial
Requires-Dist: matplotlib
Requires-Dist: seaborn
Requires-Dist: pandas-datareader
Requires-Dist: datetime
Requires-Dist: plotly
